anybadge_server.py
anybadge/__init__.py
anybadge/__main__.py
anybadge/badge.py
anybadge/cli.py
anybadge/colors.py
anybadge/config.py
anybadge/exceptions.py
anybadge/helpers.py
anybadge/styles.py
anybadge/server/__init__.py
anybadge/server/__main__.py
anybadge/server/cli.py
anybadge/server/config.py
anybadge/server/request_handler.py
anybadge/templates/__init__.py
anybadge/templates/default.svg
anybadge/templates/gitlab_scoped.svg
anybadge-1.15.6.dist-info/AUTHORS.rst
anybadge-1.15.6.dist-info/LICENSE
anybadge-1.15.6.dist-info/METADATA
anybadge-1.15.6.dist-info/WHEEL
anybadge-1.15.6.dist-info/entry_points.txt
anybadge-1.15.6.dist-info/top_level.txt
anybadge-1.15.6.dist-info/RECORD
