Metadata-Version: 2.1
Name: anybadge
Version: 1.15.6
Summary: Simple, flexible badge generator for project badges.
Home-page: https://github.com/jongracecox/anybadge
Author: Jon Grace-Cox
Author-email: 30441316+jongracecox@users.noreply.github.com
Classifier: License :: OSI Approved :: MIT License
Requires-Python: >=3.7
License-File: LICENSE
License-File: AUTHORS.rst
Requires-Dist: packaging
